bestbuyapi/__init__.py
bestbuyapi/api/__init__.py
bestbuyapi/api/base.py
bestbuyapi/api/bulk.py
bestbuyapi/api/categories.py
bestbuyapi/api/products.py
bestbuyapi/api/stores.py
bestbuyapi/constants.py
bestbuyapi/utils/__init__.py
bestbuyapi/utils/exceptions.py
bestbuyapi-2.0.0.dist-info/LICENSE
bestbuyapi-2.0.0.dist-info/WHEEL
bestbuyapi-2.0.0.dist-info/METADATA
bestbuyapi-2.0.0.dist-info/RECORD
