Metadata-Version: 2.1
Name: bestbuyapi
Version: 2.0.0
Summary: Python Wrapper over Best Buy's REST API
Home-page: https://github.com/lv10/bestbuyapi
License: MIT
Author: lv10
Author-email: luis@lv10.me
Requires-Python: >=3.6,<4.0
Classifier: Development Status :: 5 - Production/Stable
Classifier: License :: OSI Approved :: MIT License
Classifier: Programming Language :: Python :: 3
Classifier: Programming Language :: Python :: 3.6
Classifier: Programming Language :: Python :: 3.7
Classifier: Programming Language :: Python :: 3.8
Classifier: Programming Language :: Python :: 3.9
Classifier: Topic :: Software Development :: Build Tools
Classifier: Topic :: Software Development :: Libraries :: Python Modules
Requires-Dist: requests (>=2.25.1,<3.0.0)
Project-URL: Repository, https://github.com/lv10/bestbuyapi
